{
  "publicPath": "/_nuxt/",
  "all": [
    "../server/index.spa.html",
    "1a7565ed5bf681811844.js",
    "2cfb15d391980446c83d.js",
    "421634dc54081d9c75a7.js",
    "441c5fc7e8059a656c68.js",
    "5083d481a877b627ebc5.js",
    "5871ee8d92c9bf1735a5.js",
    "67da664d72526d32a35b.js",
    "8363561a08f9b8d1de52.js",
    "8398f91769ea97831d14.js",
    "85dd209ecad9d5d21a32.js",
    "8a2b26c5b097f6796b0e.js",
    "LICENSES",
    "a2e168edafbaed185587.js",
    "b13cc0a9a20893b9f059.js",
    "e328858fa1bf9b2411a3.js",
    "e5edc28a4ce46cb1fc46.js",
    "e9b07a79c2be874bf945.js",
    "f7daa6bebb3c99855095.js",
    "fbc8b2d6a32abaa0a255.js"
  ],
  "initial": [
    "8a2b26c5b097f6796b0e.js",
    "85dd209ecad9d5d21a32.js",
    "b13cc0a9a20893b9f059.js",
    "a2e168edafbaed185587.js"
  ],
  "async": [
    "1a7565ed5bf681811844.js",
    "2cfb15d391980446c83d.js",
    "421634dc54081d9c75a7.js",
    "441c5fc7e8059a656c68.js",
    "5083d481a877b627ebc5.js",
    "5871ee8d92c9bf1735a5.js",
    "67da664d72526d32a35b.js",
    "8363561a08f9b8d1de52.js",
    "8398f91769ea97831d14.js",
    "e328858fa1bf9b2411a3.js",
    "e5edc28a4ce46cb1fc46.js",
    "e9b07a79c2be874bf945.js",
    "f7daa6bebb3c99855095.js",
    "fbc8b2d6a32abaa0a255.js"
  ],
  "modules": {
    "24380085": [
      10
    ],
    "34282446": [
      13
    ],
    "55091852": [
      6
    ],
    "70211157": [
      10
    ],
    "74927109": [
      10
    ],
    "76834603": [
      19
    ],
    "5d1b805b": [
      10
    ],
    "ef5526ec": [
      13
    ],
    "5e92a408": [
      10
    ],
    "b58b56fc": [
      10
    ],
    "6939f679": [
      10
    ],
    "672c4c2a": [
      10
    ],
    "f9cebed0": [
      14
    ],
    "7932d154": [
      14
    ],
    "3fab1442": [
      10
    ],
    "2b8fd1e8": [
      14
    ],
    "14c2f0e4": [
      14
    ],
    "0a5b3304": [
      10
    ],
    "0e5d1139": [
      10
    ],
    "1887072c": [
      10
    ],
    "65afbcff": [
      10
    ],
    "0992a99d": [
      10
    ],
    "3b614d4c": [
      10
    ],
    "049040be": [
      10
    ],
    "040395e4": [
      10
    ],
    "b661384c": [
      14
    ],
    "308da294": [
      14
    ],
    "261614d9": [
      14
    ],
    "f8a989da": [
      14
    ],
    "34d9bd67": [
      10
    ],
    "62d7b7d2": [
      14
    ],
    "c340ca2c": [
      14
    ],
    "7a063f7c": [
      14
    ],
    "9d77595e": [
      10
    ],
    "369cf682": [
      10
    ],
    "5c1ce322": [
      10
    ],
    "637954c9": [
      13
    ],
    "45ef41aa": [
      13
    ],
    "d3b9a4fa": [
      13
    ],
    "ca4411ea": [
      13
    ],
    "5d999d32": [
      13
    ],
    "d7f7bb8c": [
      13
    ],
    "44c8c3b2": [
      13
    ],
    "3e811ea5": [
      13
    ],
    "1802dad7": [
      13
    ],
    "d32ee3f6": [
      13
    ],
    "14a79a9c": [
      13
    ],
    "5cd94502": [
      13
    ],
    "25b16da0": [
      13
    ],
    "854252ea": [
      13
    ],
    "673f7d8b": [
      13
    ],
    "51a3de7c": [
      13
    ],
    "84bade84": [
      13
    ],
    "14d2f00d": [
      13
    ],
    "5a4241bd": [
      13
    ],
    "0b431bf0": [
      13
    ],
    "7d207893": [
      13
    ],
    "b45466f2": [
      13
    ],
    "166fac18": [
      10
    ],
    "8cfbffee": [
      10
    ],
    "321df7a4": [
      10
    ],
    "e9d68fb2": [
      10
    ],
    "372460aa": [
      10
    ],
    "0af26457": [
      10
    ],
    "74e6ed58": [
      10
    ],
    "f8cafd0c": [
      10
    ],
    "66bf0d10": [
      10
    ],
    "6deb5802": [
      10
    ],
    "f9684572": [
      10
    ],
    "7108b4ac": [
      10
    ],
    "5a45b8d2": [
      10
    ],
    "523cb4f2": [
      10
    ],
    "74099d06": [
      10
    ],
    "f369e3c8": [
      10
    ],
    "43b2d44d": [
      10
    ],
    "3c439d2e": [
      10
    ],
    "0b2fc86d": [
      14
    ],
    "44bf395a": [
      14
    ],
    "6d75984b": [
      14
    ],
    "37dd49ba": [
      14
    ],
    "0b05927d": [
      10
    ],
    "01b7ea0b": [
      10
    ],
    "e90897ec": [
      10
    ],
    "27d0a4a7": [
      10
    ],
    "390ffb12": [
      10
    ],
    "1359603e": [
      10
    ],
    "e12d5d34": [
      10
    ],
    "bca4ba9e": [
      10
    ],
    "757a0c58": [
      10
    ],
    "80ee277e": [
      10
    ],
    "7a8d90ef": [
      10
    ],
    "0600c3cd": [
      10
    ],
    "3b19fcc8": [
      10
    ],
    "4e0b07aa": [
      14
    ],
    "096b6ce6": [
      14
    ],
    "28aebc31": [
      10
    ],
    "62a7da06": [
      10
    ],
    "71eabd1c": [
      10
    ],
    "173474f7": [
      10
    ],
    "1c7057b0": [
      10
    ],
    "e97f3c10": [
      10
    ],
    "060309a8": [
      10
    ],
    "05fc3817": [
      10
    ],
    "bda9f75c": [
      10
    ],
    "73589e9a": [
      10
    ],
    "3e509dd3": [
      10
    ],
    "afb78760": [
      10
    ],
    "c39d268c": [
      10
    ],
    "8f71a90c": [
      13
    ],
    "71e2dd00": [
      13
    ],
    "7c687864": [
      10
    ],
    "d1a81334": [
      10
    ],
    "ea190bce": [
      10
    ],
    "30328f56": [
      10
    ],
    "4d298630": [
      10
    ],
    "0d1e0de8": [
      10
    ],
    "841c17e8": [
      10
    ],
    "86d80a16": [
      10
    ],
    "0c7fef78": [
      10
    ],
    "3caa335a": [
      14
    ],
    "231e00c1": [
      13
    ],
    "691c483f": [
      14
    ],
    "7a068752": [
      14
    ],
    "4d5891cc": [
      14
    ],
    "d58b8ea6": [
      14
    ],
    "bbf2d75e": [
      14
    ],
    "625b2fe0": [
      14
    ],
    "90d2ba44": [
      14
    ],
    "f0df9c72": [
      14
    ],
    "5672029a": [
      14
    ],
    "b264b810": [
      14
    ],
    "caa97ba0": [
      14
    ],
    "a43b2de6": [
      14
    ],
    "249afb05": [
      14
    ],
    "d72456b4": [
      14
    ],
    "65ab76e8": [
      14
    ],
    "2c98824b": [
      14
    ],
    "7276549c": [
      14
    ],
    "40f0fd2f": [
      14
    ],
    "68ac888e": [
      14
    ],
    "26dd39de": [
      14
    ],
    "1f44ef54": [
      14
    ],
    "3f94d458": [
      14
    ],
    "5a444ff6": [
      14
    ],
    "2340c262": [
      14
    ],
    "59e04e52": [
      14
    ],
    "3ba95770": [
      14
    ],
    "d747eb4a": [
      14
    ],
    "671b2a34": [
      14
    ],
    "0801286d": [
      14
    ],
    "368e5f32": [
      14
    ],
    "25ac59ca": [
      14
    ],
    "2568aee9": [
      14
    ],
    "0d2008aa": [
      14
    ],
    "419b4b10": [
      14
    ],
    "320d87f0": [
      10
    ],
    "a74e3bc8": [
      10
    ],
    "d13a721e": [
      10
    ],
    "3b7a7ae0": [
      10
    ],
    "73d11938": [
      10
    ],
    "3988a7e4": [
      10
    ],
    "3bb490a4": [
      10
    ],
    "21fbe654": [
      10
    ],
    "00bb4276": [
      10
    ],
    "937662e4": [
      10
    ],
    "13eb2977": [
      10
    ],
    "1095bebc": [
      10
    ],
    "2d3060ae": [
      10
    ],
    "592f28dc": [
      10
    ],
    "d0f58e8a": [
      10
    ],
    "17d39448": [
      10
    ],
    "f434c09c": [
      10
    ],
    "4211804c": [
      10
    ],
    "2c986d2d": [
      10
    ],
    "ee7dbb8e": [
      10
    ],
    "7f405ed9": [
      10
    ],
    "5267ec88": [
      10
    ],
    "2f084196": [
      10
    ],
    "98d4a614": [
      10
    ],
    "1a58f487": [
      10
    ],
    "650684de": [
      14
    ],
    "472c0fec": [
      10
    ],
    "54a713aa": [
      10
    ],
    "7110eb47": [
      10
    ],
    "2d0ddbe9": [
      10
    ],
    "7c0cf64d": [
      10
    ],
    "2db4eef5": [
      10
    ],
    "ad467c60": [
      10
    ],
    "61e13fe2": [
      10
    ],
    "5b0d6f53": [
      10
    ],
    "2ca21409": [
      14
    ],
    "8eb71482": [
      10
    ],
    "00736cd4": [
      14
    ],
    "e9ccdabc": [
      14
    ],
    "566b3232": [
      13
    ],
    "6da5fbf2": [
      10
    ],
    "92e535e4": [
      10
    ],
    "5a786ea8": [
      10
    ],
    "4f8fcb72": [
      10
    ],
    "2e6061eb": [
      10
    ],
    "5f23ae33": [
      10
    ],
    "c8c15500": [
      10
    ],
    "5be688fa": [
      10
    ],
    "18bfd5ba": [
      10
    ],
    "12ef00c0": [
      10
    ],
    "a8b2edba": [
      13
    ],
    "6b350430": [
      13
    ],
    "f5bfda02": [
      10
    ],
    "c1e3c37e": [
      10
    ],
    "667c6b34": [
      10
    ],
    "df84ed0e": [
      10
    ],
    "0a3303cc": [
      10
    ],
    "07552c10": [
      10
    ],
    "6b992395": [
      10
    ],
    "724da308": [
      10
    ],
    "c4cf41d2": [
      10
    ],
    "494a1698": [
      10
    ],
    "2aa3c500": [
      10
    ],
    "013a9a4a": [
      10
    ],
    "97cbead8": [
      10
    ],
    "4817ac24": [
      10
    ],
    "159c507e": [
      10
    ],
    "66e50b72": [
      10
    ],
    "322f0e4a": [
      10
    ],
    "36a28c47": [
      10
    ],
    "7c583ba4": [
      10
    ],
    "2d82ce23": [
      10
    ],
    "10b1a29a": [
      10
    ],
    "99005fd4": [
      10
    ],
    "620f35a4": [
      13
    ],
    "549fcb96": [
      13
    ],
    "6371c0fa": [
      13
    ],
    "1cd92d62": [
      13
    ],
    "4da9bf7d": [
      14
    ],
    "20fcc888": [
      14
    ],
    "7574affd": [
      14
    ],
    "c6f04588": [
      14
    ],
    "b0d63a60": [
      10
    ],
    "e02dfc3a": [
      10
    ],
    "f1c99f2e": [
      10
    ],
    "02fc5092": [
      14
    ],
    "7e12e173": [
      14
    ],
    "627d6a8c": [
      10
    ],
    "260703ec": [
      10
    ],
    "160be9ec": [
      10
    ],
    "7a7aed40": [
      10
    ],
    "3e2b6feb": [
      10
    ],
    "2063e8df": [
      10
    ],
    "8a881a4e": [
      10
    ],
    "a0db4934": [
      10
    ],
    "7b8b9cac": [
      10
    ],
    "02db9c67": [
      10
    ],
    "19d784f4": [
      10
    ],
    "cbb99efe": [
      10
    ],
    "5efaa832": [
      10
    ],
    "5f206e98": [
      10
    ],
    "cd4e214c": [
      10
    ],
    "620927d8": [
      10
    ],
    "463b9da3": [
      10
    ],
    "0d94cc55": [
      10
    ],
    "337c8135": [
      10
    ],
    "1d045dd7": [
      10
    ],
    "2ead8cbc": [
      10
    ],
    "b7981616": [
      10
    ],
    "63c11e63": [
      14
    ],
    "2af8183a": [
      14
    ],
    "7ee5344e": [
      14
    ],
    "e9e78d60": [
      5
    ],
    "319660ba": [
      19
    ],
    "381f2b27": [
      5
    ],
    "7fd1cde2": [
      18
    ],
    "2b1132d7": [
      5
    ],
    "15a355f1": [
      5
    ],
    "59da945a": [
      2
    ],
    "744e92b3": [
      6
    ],
    "21ec0b6b": [
      15
    ],
    "0e5977c2": [
      15
    ],
    "78abd90c": [
      15
    ],
    "05063114": [
      15
    ],
    "347d8242": [
      5
    ],
    "e9204098": [
      5
    ],
    "9c7beb1c": [
      15
    ],
    "6de1dea3": [
      2
    ],
    "19e5f813": [
      2
    ],
    "1eec7f14": [
      2
    ],
    "02ba96fa": [
      2
    ],
    "9eec712a": [
      15
    ],
    "0bb249a0": [
      15
    ],
    "0ca43115": [
      15
    ],
    "348c673a": [
      5
    ],
    "599163e0": [
      5
    ],
    "3a98d574": [
      5
    ],
    "a7c1773e": [
      15
    ],
    "2e51305b": [
      15
    ],
    "b445cd3c": [
      5
    ],
    "724a2c9a": [
      15
    ],
    "25ec4bd8": [
      5
    ],
    "1ebb02d2": [
      5
    ],
    "049d93c6": [
      2
    ],
    "72ef2825": [
      15
    ],
    "6c0c2330": [
      15
    ],
    "01eea3ce": [
      15
    ],
    "08442570": [
      15
    ],
    "80023d6e": [
      15
    ],
    "69a28ecb": [
      15
    ],
    "52ddaa4b": [
      15
    ],
    "3f32ef86": [
      2
    ],
    "3ab3157c": [
      2
    ],
    "bd254cf6": [
      2
    ],
    "a953327a": [
      2
    ],
    "6d8c03e7": [
      2
    ],
    "709ff412": [
      2
    ],
    "100e6405": [
      15
    ],
    "3a17cb90": [
      15
    ],
    "033d6992": [
      15
    ],
    "4a62176f": [
      19
    ],
    "4275b856": [
      15
    ],
    "10406c04": [
      2
    ],
    "b9a1f4fa": [
      15
    ],
    "11a83747": [
      15
    ],
    "16a02a92": [
      15
    ],
    "1c405a7e": [
      15
    ],
    "0e143b2b": [
      15
    ],
    "63dcbcca": [
      2
    ],
    "fb369bfa": [
      2
    ],
    "785ba293": [
      5
    ],
    "41c80afd": [
      5
    ],
    "3fc9afbc": [
      5
    ],
    "3aef5d0a": [
      5
    ],
    "5af67753": [
      5
    ],
    "1d296a74": [
      5
    ],
    "693a5e9d": [
      15
    ],
    "0b123adc": [
      15
    ],
    "dba042de": [
      15
    ],
    "6ac04be0": [
      15
    ],
    "6e6c8c49": [
      19
    ],
    "0c835670": [
      19
    ],
    "47bfe485": [
      15
    ],
    "7f8110f8": [
      15
    ],
    "4d5fa64e": [
      19
    ],
    "5d7b9dd8": [
      19
    ],
    "02300bc6": [
      19
    ],
    "25fb275c": [
      19
    ],
    "2a1a6add": [
      18
    ],
    "0d46e09c": [
      18
    ],
    "78da0408": [
      2
    ],
    "12a78d5d": [
      2
    ],
    "10a9321c": [
      2
    ],
    "eb229112": [
      2
    ],
    "15c07ff6": [
      2
    ],
    "5f50089d": [
      2
    ],
    "5d51ad5c": [
      2
    ],
    "1a6db3d1": [
      2
    ],
    "6d2ae560": [
      2
    ],
    "06346ec6": [
      2
    ],
    "23f8f5dc": [
      2
    ],
    "63eb2c9d": [
      6
    ],
    "4717a25c": [
      6
    ],
    "23feefac": [
      6
    ],
    "0c6c6deb": [
      6
    ],
    "18c00d50": [
      6
    ],
    "c8721062": [
      6
    ],
    "90efd136": [
      6
    ],
    "fd23cd38": [
      6
    ],
    "7100ee04": [
      17
    ],
    "6fe460c3": [
      15
    ],
    "174a4cdd": [
      15
    ],
    "3bd2524b": [
      6
    ],
    "05843de4": [
      6
    ],
    "2548ed1c": [
      6
    ],
    "127ad594": [
      6
    ],
    "75073ebc": [
      6
    ],
    "44bc3836": [
      6
    ],
    "7612a10b": [
      6
    ],
    "31041b03": [
      6
    ],
    "58127e44": [
      6
    ],
    "c9db76f8": [
      6
    ],
    "7ef580f4": [
      6
    ],
    "5c8a8d5c": [
      6
    ],
    "52fbace3": [
      6
    ],
    "22cc23cc": [
      6
    ],
    "093868b6": [
      6
    ],
    "8a59858a": [
      6
    ],
    "543a531f": [
      6
    ],
    "29e14c66": [
      6
    ],
    "6d1c292a": [
      18
    ],
    "15943b99": [
      18
    ],
    "1a9fdf5c": [
      18
    ],
    "28ced1c2": [
      18
    ],
    "3157b2c8": [
      18
    ],
    "ab242d7a": [
      18
    ],
    "4ea8e928": [
      16
    ],
    "6a99a535": [
      16
    ],
    "347e651e": [
      16
    ],
    "7513f98a": [
      16
    ],
    "6e8d4d3b": [
      16
    ],
    "1a527df2": [
      8
    ],
    "1a240678": [
      8
    ],
    "6d546dab": [
      8
    ],
    "ff00cf04": [
      8
    ],
    "6d67cd16": [
      8
    ],
    "1b2f4cf6": [
      9
    ],
    "6d8a77fd": [
      9
    ],
    "b7cda370": [
      9
    ],
    "309f3f92": [
      9
    ],
    "024d1384": [
      9
    ],
    "44d69ffc": [
      3
    ],
    "05ee76e6": [
      3
    ],
    "6152d09e": [
      3
    ],
    "b5a80072": [
      3
    ],
    "7fb416b2": [
      3
    ],
    "4352b565": [
      1
    ],
    "f13036be": [
      1
    ],
    "6ba7ef30": [
      1
    ],
    "2702d94a": [
      1
    ],
    "25ac5444": [
      1
    ],
    "73853a8f": [
      4
    ],
    "1c7219e3": [
      4
    ],
    "021ae9ae": [
      4
    ],
    "ad15492e": [
      4
    ],
    "92122c10": [
      4
    ],
    "61920f76": [
      7
    ],
    "6f9543b2": [
      7
    ],
    "6296fea7": [
      7
    ],
    "45999f38": [
      7
    ],
    "573b14f1": [
      7
    ],
    "3a3b7e7f": [
      19
    ],
    "f4a5dafa": [
      19
    ],
    "4a642f82": [
      19
    ]
  },
  "assetsMapping": {
    "1a7565ed5bf681811844.js": "63c204a6",
    "2cfb15d391980446c83d.js": "c78e293a",
    "421634dc54081d9c75a7.js": "7ea92bfd",
    "441c5fc7e8059a656c68.js": "56372ee1",
    "5083d481a877b627ebc5.js": "47ef5927",
    "5871ee8d92c9bf1735a5.js": "74a55600",
    "67da664d72526d32a35b.js": "e2463b36",
    "8363561a08f9b8d1de52.js": "ef092df2",
    "8398f91769ea97831d14.js": "df9172f4",
    "85dd209ecad9d5d21a32.js": "0859c165",
    "8a2b26c5b097f6796b0e.js": "6fca0322",
    "a2e168edafbaed185587.js": "1a3ae26b",
    "b13cc0a9a20893b9f059.js": "7ea1d828",
    "e328858fa1bf9b2411a3.js": "76525739",
    "e5edc28a4ce46cb1fc46.js": "3cdf16e1",
    "e9b07a79c2be874bf945.js": "ff9600b4",
    "f7daa6bebb3c99855095.js": "047e7b80",
    "fbc8b2d6a32abaa0a255.js": "31bab5af"
  }
}